[
    {
        "transaction_id": "T320675497",
        "date_time": "2025-05-04 08:27:00",
        "buyer": "admin",
        "items_summary": [
            {
                "item_id": 303,
                "item_name": "V-Bucks Pack",
                "quantity": 2,
                "price_at_purchase": 500.0,
                "sub_total": 1000.0,
                "owner": "GamingHub"
            },
            {
                "item_id": 205,
                "item_name": "Coffee Grinder",
                "quantity": 1,
                "price_at_purchase": 1500.0,
                "sub_total": 1500.0,
                "owner": "Seller123"
            },
            {
                "item_id": 303,
                "item_name": "V-Bucks Pack",
                "quantity": 1,
                "price_at_purchase": 500.0,
                "sub_total": 500.0,
                "owner": "GamingHub"
            }
        ],
        "total_price": 3000.0,
        "pay_amount": 3100.0,
        "change": 100.0,
        "payment_method": "SPayLater"
    },
    {
        "transaction_id": "T462255520",
        "date_time": "2025-05-04 15:26:00",
        "buyer": "eli",
        "items_summary": [
            {
                "item_id": 303,
                "item_name": "V-Bucks Pack",
                "quantity": 2,
                "price_at_purchase": 500.0,
                "sub_total": 1000.0,
                "owner": "GamingHub"
            },
            {
                "item_id": 101,
                "item_name": "Mechanical Keyboard",
                "quantity": 3,
                "price_at_purchase": 2500.0,
                "sub_total": 7500.0,
                "owner": "TechStore"
            },
            {
                "item_id": 401,
                "item_name": "Robux Gift Card",
                "quantity": 2,
                "price_at_purchase": 250.0,
                "sub_total": 500.0,
                "owner": "GamingHub"
            }
        ],
        "total_price": 9000.0,
        "pay_amount": 10000.0,
        "change": 1000.0,
        "payment_method": "GCash"
    },
    {
        "transaction_id": "T964368673",
        "date_time": "2025-05-04 07:39:00",
        "buyer": "ae",
        "items_summary": [
            {
                "item_id": 303,
                "item_name": "V-Bucks Pack",
                "quantity": 3,
                "price_at_purchase": 500.0,
                "sub_total": 1500.0,
                "owner": "GamingHub"
            }
        ],
        "total_price": 1500.0,
        "pay_amount": 1600.0,
        "change": 100.0,
        "payment_method": "Credit Card"
    },
    {
        "transaction_id": "T524769428",
        "date_time": "2025-05-04 21:53:00",
        "buyer": "ae",
        "items_summary": [
            {
                "item_id": 303,
                "item_name": "V-Bucks Pack",
                "quantity": 3,
                "price_at_purchase": 500.0,
                "sub_total": 1500.0,
                "owner": "GamingHub"
            }
        ],
        "total_price": 1500.0,
        "pay_amount": 1550.0,
        "change": 50.0,
        "payment_method": "Credit Card"
    },
    {
        "transaction_id": "T675181808",
        "date_time": "2025-05-04 08:07:00",
        "buyer": "ae",
        "items_summary": [
            {
                "item_id": 202,
                "item_name": "Espresso Beans",
                "quantity": 1,
                "price_at_purchase": 450.0,
                "sub_total": 450.0,
                "owner": "Seller123"
            }
        ],
        "total_price": 450.0,
        "pay_amount": 950.0,
        "change": 500.0,
        "payment_method": "GCash"
    },
    {
        "transaction_id": "T638073549",
        "date_time": "2025-05-04 10:03:00",
        "buyer": "admin",
        "items_summary": [
            {
                "item_id": 305,
                "item_name": "Minecoins",
                "quantity": 3,
                "price_at_purchase": 50.0,
                "sub_total": 150.0,
                "owner": "GamingHub"
            }
        ],
        "total_price": 150.0,
        "pay_amount": 200.0,
        "change": 50.0,
        "payment_method": "GCash"
    },
    {
        "transaction_id": "T691071579",
        "date_time": "2025-05-04 11:54:00",
        "buyer": "ae",
        "items_summary": [
            {
                "item_id": 101,
                "item_name": "Mechanical Keyboard",
                "quantity": 1,
                "price_at_purchase": 2500.0,
                "sub_total": 2500.0,
                "owner": "TechStore"
            },
            {
                "item_id": 101,
                "item_name": "Mechanical Keyboard",
                "quantity": 1,
                "price_at_purchase": 2500.0,
                "sub_total": 2500.0,
                "owner": "TechStore"
            },
            {
                "item_id": 202,
                "item_name": "Espresso Beans",
                "quantity": 2,
                "price_at_purchase": 450.0,
                "sub_total": 900.0,
                "owner": "Seller123"
            },
            {
                "item_id": 303,
                "item_name": "V-Bucks Pack",
                "quantity": 1,
                "price_at_purchase": 500.0,
                "sub_total": 500.0,
                "owner": "GamingHub"
            }
        ],
        "total_price": 6400.0,
        "pay_amount": 6450.0,
        "change": 50.0,
        "payment_method": "Bank Transfer"
    },
    {
        "transaction_id": "T151454032",
        "date_time": "2025-05-04 18:50:00",
        "buyer": "ae",
        "items_summary": [
            {
                "item_id": 205,
                "item_name": "Coffee Grinder",
                "quantity": 2,
                "price_at_purchase": 1500.0,
                "sub_total": 3000.0,
                "owner": "Seller123"
            },
            {
                "item_id": 101,
                "item_name": "Mechanical Keyboard",
                "quantity": 3,
                "price_at_purchase": 2500.0,
                "sub_total": 7500.0,
                "owner": "TechStore"
            }
        ],
        "total_price": 10500.0,
        "pay_amount": 10550.0,
        "change": 50.0,
        "payment_method": "Credit Card"
    }
]